diskhashtree/DiskHashTree.py
diskhashtree/__init__.py
diskhashtree/__main__.py
diskhashtree/util.py
diskhashtree-1.0.1.dist-info/LICENSE
diskhashtree-1.0.1.dist-info/METADATA
diskhashtree-1.0.1.dist-info/WHEEL
diskhashtree-1.0.1.dist-info/entry_points.txt
diskhashtree-1.0.1.dist-info/top_level.txt
diskhashtree-1.0.1.dist-info/RECORD
