Metadata-Version: 2.1
Name: diskhashtree
Version: 1.0.1
Summary: A class for managing on-disk hash trees.
Home-page: https://gitlab.com/delta1512/disk-hash-tree
Author: Marcus Belcastro
Author-email: markbel555@gmail.com
License: GNU GPLv3
Project-URL: Donate, https://gitlab.com/delta1512/donations
Project-URL: Source Code, https://gitlab.com/delta1512/disk-hash-tree
Project-URL: Twitter, https://twitter.com/delta_1512
Platform: UNKNOWN
License-File: LICENSE
